<?xml version="1.0" encoding="UTF-8"?>
<objects serializationModel="Studio.02.03.00">
	<object class="AudioFile" id="{96411389-e769-40be-83a8-e588ff02ddb8}">
		<property name="assetPath">
			<value>Demons/Crawler-20250731T061309Z-1-001/Crawler/Fleshball (Charge).wav</value>
		</property>
		<property name="frequencyInKHz">
			<value>44.0999985</value>
		</property>
		<property name="channelCount">
			<value>2</value>
		</property>
		<property name="length">
			<value>4.2516553287981855</value>
		</property>
		<relationship name="masterAssetFolder">
			<destination>{821c9465-3e60-4771-8724-d7080c7c16fb}</destination>
		</relationship>
	</object>
</objects>
